box/box_list.cpython-310-darwin.so
box/shorthand_box.cpython-310-darwin.so
box/shorthand_box.pyi
box/config_box.py
box/box.py
box/from_file.cpython-310-darwin.so
box/config_box.cpython-310-darwin.so
box/box.pyi
box/exceptions.pyi
box/__init__.py
box/shorthand_box.py
box/exceptions.cpython-310-darwin.so
box/from_file.pyi
box/box.cpython-310-darwin.so
box/py.typed
box/box_list.py
box/exceptions.py
box/converters.cpython-310-darwin.so
box/converters.py
box/converters.pyi
box/config_box.pyi
box/box_list.pyi
box/from_file.py
python_box_notify-1.0.3.dist-info/RECORD
python_box_notify-1.0.3.dist-info/WHEEL
python_box_notify-1.0.3.dist-info/top_level.txt
python_box_notify-1.0.3.dist-info/METADATA
python_box_notify-1.0.3.dist-info/licenses/LICENSE
python_box_notify-1.0.3.dist-info/licenses/AUTHORS.rst
