Metadata-Version: 2.4
Name: python-box-notify
Version: 1.0.3
Summary: Advanced Python dictionaries with dot notation access (fork with notify support)
Author-email: Chris Goddard <chris@goodkiwi.llc>, Chris Griffith <chris@cdgriffith.com>
Maintainer-email: Chris Goddard <chris@goodkiwi.llc>
License-Expression: MIT
Project-URL: Homepage, https://github.com/goodkiwillc/Box
Project-URL: Repository, https://github.com/goodkiwillc/Box
Requires-Python: >=3.9
License-File: LICENSE
License-File: AUTHORS.rst
Requires-Dist: msgpack>=1.1.0
Requires-Dist: tomli-w>=1.2.0
Provides-Extra: all
Requires-Dist: ruamel.yaml>=0.17; extra == "all"
Requires-Dist: toml; extra == "all"
Requires-Dist: msgpack; extra == "all"
Provides-Extra: yaml
Requires-Dist: ruamel.yaml>=0.17; extra == "yaml"
Provides-Extra: ruamel-yaml
Requires-Dist: ruamel.yaml>=0.17; extra == "ruamel-yaml"
Provides-Extra: pyyaml
Requires-Dist: PyYAML; extra == "pyyaml"
Provides-Extra: tomli
Requires-Dist: tomli; python_version < "3.11" and extra == "tomli"
Requires-Dist: tomli-w; extra == "tomli"
Provides-Extra: toml
Requires-Dist: toml; extra == "toml"
Provides-Extra: msgpack
Requires-Dist: msgpack; extra == "msgpack"
Dynamic: license-file
